aliyunsdkvideoenhan/__init__.py
aliyunsdkvideoenhan/endpoint.py
aliyunsdkvideoenhan/request/__init__.py
aliyunsdkvideoenhan/request/v20200320/AbstractEcommerceVideoRequest.py
aliyunsdkvideoenhan/request/v20200320/AbstractFilmVideoRequest.py
aliyunsdkvideoenhan/request/v20200320/AddFaceVideoTemplateRequest.py
aliyunsdkvideoenhan/request/v20200320/AdjustVideoColorRequest.py
aliyunsdkvideoenhan/request/v20200320/ChangeVideoSizeRequest.py
aliyunsdkvideoenhan/request/v20200320/ConvertHdrVideoRequest.py
aliyunsdkvideoenhan/request/v20200320/DeleteFaceVideoTemplateRequest.py
aliyunsdkvideoenhan/request/v20200320/EnhancePortraitVideoRequest.py
aliyunsdkvideoenhan/request/v20200320/EnhanceVideoQualityRequest.py
aliyunsdkvideoenhan/request/v20200320/EraseVideoLogoRequest.py
aliyunsdkvideoenhan/request/v20200320/EraseVideoSubtitlesRequest.py
aliyunsdkvideoenhan/request/v20200320/GenerateHumanAnimeStyleVideoRequest.py
aliyunsdkvideoenhan/request/v20200320/GenerateVideoRequest.py
aliyunsdkvideoenhan/request/v20200320/GetAsyncJobResultRequest.py
aliyunsdkvideoenhan/request/v20200320/InterpolateVideoFrameRequest.py
aliyunsdkvideoenhan/request/v20200320/MergeVideoFaceRequest.py
aliyunsdkvideoenhan/request/v20200320/MergeVideoModelFaceRequest.py
aliyunsdkvideoenhan/request/v20200320/QueryFaceVideoTemplateRequest.py
aliyunsdkvideoenhan/request/v20200320/ReduceVideoNoiseRequest.py
aliyunsdkvideoenhan/request/v20200320/SuperResolveVideoRequest.py
aliyunsdkvideoenhan/request/v20200320/ToneSdrVideoRequest.py
aliyunsdkvideoenhan/request/v20200320/__init__.py
aliyun_python_sdk_videoenhan-1.0.24.dist-info/LICENSE
aliyun_python_sdk_videoenhan-1.0.24.dist-info/METADATA
aliyun_python_sdk_videoenhan-1.0.24.dist-info/WHEEL
aliyun_python_sdk_videoenhan-1.0.24.dist-info/top_level.txt
aliyun_python_sdk_videoenhan-1.0.24.dist-info/RECORD
